hex.py
setup.py
hex.egg-info/PKG-INFO
hex.egg-info/SOURCES.txt
hex.egg-info/dependency_links.txt
hex.egg-info/entry_points.txt
hex.egg-info/top_level.txt