Metadata-Version: 1.1
Name: hex
Version: 2.0.0
Summary: Hexdump command line utility.
Home-page: https://github.com/dmulholland/hex
Author: Darren Mulholland
Author-email: UNKNOWN
License: Public Domain
Platform: UNKNOWN
Classifier: Development Status :: 5 - Production/Stable
Classifier: Programming Language :: Python :: 3
Classifier: Operating System :: OS Independent
Classifier: License :: Public Domain
Classifier: Topic :: Utilities
